tadata_sdk/__init__.py
tadata_sdk/types.py
tadata_sdk/core/__init__.py
tadata_sdk/core/sdk.py
tadata_sdk/errors/__init__.py
tadata_sdk/errors/exceptions.py
tadata_sdk/http/__init__.py
tadata_sdk/http/client.py
tadata_sdk/http/schemas.py
tadata_sdk/openapi/__init__.py
tadata_sdk/openapi/source.py
tadata_sdk-0.1.0.dist-info/METADATA
tadata_sdk-0.1.0.dist-info/WHEEL
tadata_sdk-0.1.0.dist-info/RECORD
