Metadata-Version: 2.4
Name: tadata-sdk
Version: 0.1.0
Summary: Tadata Python SDK
Project-URL: Homepage, https://github.com/tadata-org/tadata-python-sdk
Project-URL: Documentation, https://github.com/tadata-org/tadata-python-sdk#readme
Project-URL: Bug Tracker, https://github.com/tadata-org/tadata-python-sdk/issues
Project-URL: PyPI, https://pypi.org/project/tadata-python-sdk/
Project-URL: Source Code, https://github.com/tadata-org/tadata-python-sdk
Project-URL: Changelog, https://github.com/tadata-org/tadata-python-sdk/blob/main/CHANGELOG.md
Author: Tadata Inc.
Keywords: llm,mcp,modelcontextprotocol,openapi,tadata
Classifier: Programming Language :: Python :: 3
Classifier: Programming Language :: Python :: 3.10
Classifier: Programming Language :: Python :: 3.11
Classifier: Programming Language :: Python :: 3.12
Classifier: Programming Language :: Python :: 3.13
Requires-Python: >=3.10
Requires-Dist: httpx>=0.24.0
Requires-Dist: pydantic-settings>=2.5.2
Requires-Dist: pydantic>=2.0.0
Requires-Dist: pyyaml>=6.0
Requires-Dist: tomli>=2.2.1
